[
    {
        "nome": "605",
        "pontuacao": 1748605
    },
    {
        "nome": "3605",
        "pontuacao": 3605
    },
    {
        "nome": "a",
        "pontuacao": 3505
    },
    {
        "nome": "1067",
        "pontuacao": 3067
    },
    {
        "nome": "rafa",
        "pontuacao": 3036
    },
    {
        "nome": "brabo",
        "pontuacao": 3028
    },
    {
        "nome": "e",
        "pontuacao": 2023
    },
    {
        "nome": "menu",
        "pontuacao": 1057
    },
    {
        "nome": "feito",
        "pontuacao": 1057
    },
    {
        "nome": "rafaell",
        "pontuacao": 1045
    },
    {
        "nome": "a",
        "pontuacao": 1034
    },
    {
        "nome": "1026",
        "pontuacao": 1026
    },
    {
        "nome": "l",
        "pontuacao": 1022
    },
    {
        "nome": "aw",
        "pontuacao": 1021
    },
    {
        "nome": "q",
        "pontuacao": 1017
    },
    {
        "nome": "1014",
        "pontuacao": 1014
    },
    {
        "nome": "era",
        "pontuacao": 703
    },
    {
        "nome": "q",
        "pontuacao": 10
    },
    {
        "nome": "ruim",
        "pontuacao": 5
    }
]